bornagain/__init__.py
bornagain/ba_check.py
bornagain/ba_fitmonitor.py
bornagain/ba_plot.py
bornagain/numpyutil.py
bornagain/sample_tools.py
bornagain/std_samples.py
bornagain/std_simulations.py
bornagain/lib/__init__.py
bornagain/lib/_libBornAgainBase.pyd
bornagain/lib/_libBornAgainDevice.pyd
bornagain/lib/_libBornAgainFit.pyd
bornagain/lib/_libBornAgainParam.pyd
bornagain/lib/_libBornAgainPyCore.pyd
bornagain/lib/_libBornAgainResample.pyd
bornagain/lib/_libBornAgainSample.pyd
bornagain/lib/_libBornAgainSim.pyd
bornagain/lib/libBornAgainBase.py
bornagain/lib/libBornAgainDevice.py
bornagain/lib/libBornAgainFit.py
bornagain/lib/libBornAgainParam.py
bornagain/lib/libBornAgainResample.py
bornagain/lib/libBornAgainSample.py
bornagain/lib/libBornAgainSim.py
bornagain/lib/extra/bz2.dll
bornagain/lib/extra/cerfcpp.dll
bornagain/lib/extra/formfactor.dll
bornagain/lib/extra/gsl.dll
bornagain/lib/extra/gslcblas.dll
bornagain/lib/extra/libfftw3-3.dll
bornagain/lib/extra/libtiff.dll
bornagain/lib/extra/zlib.dll
bornagain-23.0.dist-info/licenses/COPYING
bornagain-23.0.dist-info/METADATA
bornagain-23.0.dist-info/WHEEL
bornagain-23.0.dist-info/top_level.txt
bornagain-23.0.dist-info/RECORD
