Metadata-Version: 2.4
Name: BornAgain
Version: 23.0
Summary: Open-source research software to simulate and fit neutron and x-ray reflectometry and grazing-incidence small-angle scattering.
Home-page: https://www.bornagainproject.org
Author: Scientific Computing Group, Forschungszentrum Jülich, MLZ, Garching
Author-email: contact@bornagainproject.org
License: GNU General Public License
Project-URL: Documentation, https://www.bornagainproject.org/documentation
Project-URL: Source, https://jugit.fz-juelich.de/mlz/bornagain
Project-URL: Tracker, https://jugit.fz-juelich.de/mlz/bornagain/-/issues
Project-URL: Changelog, https://jugit.fz-juelich.de/mlz/bornagain/-/blob/main/CHANGELOG
Project-URL: Download, https://www.bornagainproject.org/download/
Keywords: neutron,reflectometry,x-ray,scattering,simulation,data analysis
Platform: Linux
Platform: macOS
Platform: Windows
Classifier: Programming Language :: C++
Classifier: Programming Language :: Python :: 3
Classifier: Operating System :: POSIX :: Linux
Classifier: Operating System :: MacOS
Classifier: Operating System :: Microsoft :: Windows
Classifier: Development Status :: 5 - Production/Stable
Classifier: Topic :: Scientific/Engineering :: Physics
Classifier: License :: OSI Approved :: GNU General Public License (GPL)
Requires-Python: >=3.10
License-File: COPYING
Requires-Dist: matplotlib
Requires-Dist: numpy
Dynamic: license-file
